flywaymigrationconstruct/__init__.py
flywaymigrationconstruct/py.typed
flywaymigrationconstruct/_jsii/__init__.py
flywaymigrationconstruct/_jsii/flywaymigrationconstruct@0.2.45.jsii.tgz
flywaymigrationconstruct-0.2.45.dist-info/LICENSE
flywaymigrationconstruct-0.2.45.dist-info/METADATA
flywaymigrationconstruct-0.2.45.dist-info/WHEEL
flywaymigrationconstruct-0.2.45.dist-info/top_level.txt
flywaymigrationconstruct-0.2.45.dist-info/RECORD
