Metadata-Version: 2.1
Name: flywaymigrationconstruct
Version: 0.2.45
Summary: flywaymigrationconstruct
Home-page: https://github.com/APrzysiuda/flywaymigrationconstruct.git
Author: APrzysiuda<180517@umons.ac.be>
License: Apache-2.0
Project-URL: Source, https://github.com/APrzysiuda/flywaymigrationconstruct.git
Platform: UNKNOWN
Classifier: Intended Audience :: Developers
Classifier: Operating System :: OS Independent
Classifier: Programming Language :: JavaScript
Classifier: Programming Language :: Python :: 3 :: Only
Classifier: Programming Language :: Python :: 3.6
Classifier: Programming Language :: Python :: 3.7
Classifier: Programming Language :: Python :: 3.8
Classifier: Programming Language :: Python :: 3.9
Classifier: Typing :: Typed
Classifier: Development Status :: 5 - Production/Stable
Classifier: License :: OSI Approved
Requires-Python: >=3.6
License-File: LICENSE
Requires-Dist: aws-cdk.aws-ec2 (<2.0.0,>=1.125.0)
Requires-Dist: aws-cdk.aws-lambda (<2.0.0,>=1.125.0)
Requires-Dist: aws-cdk.aws-s3 (<2.0.0,>=1.125.0)
Requires-Dist: aws-cdk.aws-secretsmanager (<2.0.0,>=1.125.0)
Requires-Dist: aws-cdk.core (<2.0.0,>=1.125.0)
Requires-Dist: constructs (<4.0.0,>=3.2.27)
Requires-Dist: jsii (<2.0.0,>=1.39.0)
Requires-Dist: publication (>=0.0.3)
